com/__init__.py
com/dvsnier/__init__.py
com/dvsnier/tool/__init__.py
com/dvsnier/tool/command/__init__.py
com/dvsnier/tool/command/dvs_vscode_ws.py
com/dvsnier/tool/util/__init__.py
com/dvsnier/tool/util/dvs_logging.py
com/dvsnier/tool/util/vscode_ws.py
com.dvsnier.tools-0.0.1a1.dev1.dist-info/LICENSE
com.dvsnier.tools-0.0.1a1.dev1.dist-info/LICENSE.txt
com.dvsnier.tools-0.0.1a1.dev1.dist-info/METADATA
com.dvsnier.tools-0.0.1a1.dev1.dist-info/WHEEL
com.dvsnier.tools-0.0.1a1.dev1.dist-info/entry_points.txt
com.dvsnier.tools-0.0.1a1.dev1.dist-info/top_level.txt
com.dvsnier.tools-0.0.1a1.dev1.dist-info/RECORD
